printen
