Metadata-Version: 1.1
Name: printen
Version: 0.1.0
Summary: Flexible integration of Elasticsearch into Python projects.
Home-page: https://github.com/jimjkelly/printen
Author: James Kelly
Author-email: pthread1981@gmail.com
License: BSD
Keywords: elasticsearch search indexing flask django peewee
Platform: UNKNOWN
Classifier: Development Status :: 4 - Beta
Classifier: License :: OSI Approved :: BSD License
Classifier: Intended Audience :: Developers
Classifier: Environment :: Web Environment
Classifier: Programming Language :: Python
Classifier: Framework :: Flask
Classifier: Framework :: Django
Classifier: Topic :: Internet :: WWW/HTTP :: WSGI
Classifier: Natural Language :: English
Classifier: Programming Language :: Python :: 2
Classifier: Programming Language :: Python :: 2.7
